hmmCDR/__init__.py
hmmCDR/bed_parser.py
hmmCDR/calculate_matrices.py
hmmCDR/hmmcdr.py
hmmCDR-0.3.0.dist-info/LICENSE
hmmCDR-0.3.0.dist-info/METADATA
hmmCDR-0.3.0.dist-info/WHEEL
hmmCDR-0.3.0.dist-info/entry_points.txt
hmmCDR-0.3.0.dist-info/top_level.txt
hmmCDR-0.3.0.dist-info/RECORD
