Metadata-Version: 2.2
Name: hmmCDR
Version: 0.3.0
Summary: Find CDR locations using bedmethyl file and CenSat annotations. (REQUIRES BEDTOOLS INSTALLED)
Home-page: https://github.com/jmenendez98/hmmCDR
Author: Julian Menendez
Author-email: jmmenend@ucsc.edu
License: MIT
Project-URL: GitHub, https://github.com/jmenendez98/hmmCDR
Project-URL: Lab Website, https://migalab.com/
Classifier: Programming Language :: Python :: 3
Classifier: License :: OSI Approved :: MIT License
Classifier: Operating System :: OS Independent
Requires-Python: >=3.8, <3.13
License-File: LICENSE
Requires-Dist: numpy>=1.21.5
Requires-Dist: hmmlearn>=0.3.0
Provides-Extra: dev
Requires-Dist: pytest; extra == "dev"
Requires-Dist: pytest-cov; extra == "dev"
Requires-Dist: isort; extra == "dev"
Requires-Dist: mypy; extra == "dev"
Dynamic: author
Dynamic: author-email
Dynamic: classifier
Dynamic: description
Dynamic: description-content-type
Dynamic: home-page
Dynamic: license
Dynamic: project-url
Dynamic: provides-extra
Dynamic: requires-dist
Dynamic: requires-python
Dynamic: summary
